bitfinex_extractor_influxdb/__init__.py
bitfinex_extractor_influxdb/exchange_db_sync.py
bitfinex_extractor_influxdb-0.7.0.dist-info/LICENSE
bitfinex_extractor_influxdb-0.7.0.dist-info/METADATA
bitfinex_extractor_influxdb-0.7.0.dist-info/WHEEL
bitfinex_extractor_influxdb-0.7.0.dist-info/top_level.txt
bitfinex_extractor_influxdb-0.7.0.dist-info/RECORD
