Metadata-Version: 2.1
Name: bitfinex-extractor-influxdb
Version: 0.7.0
Summary: Python bitfinex Extractor into InfluxDB
Home-page: https://github.com/frapercan/bitfinex-extractor-influxdb.git
Author: frapercan
Author-email: frapercan1@alum.us.es
License: MIT
Platform: UNKNOWN
Classifier: Development Status :: 2 - Pre-Alpha
Classifier: License :: OSI Approved :: MIT License
Classifier: Programming Language :: Python :: 3.8
